fistminio/__init__.py
fistminio/fistapi.py
fistminio-1.0.5.dist-info/LICENSE
fistminio-1.0.5.dist-info/METADATA
fistminio-1.0.5.dist-info/WHEEL
fistminio-1.0.5.dist-info/top_level.txt
fistminio-1.0.5.dist-info/RECORD
