Metadata-Version: 2.1
Name: fistminio
Version: 1.0.5
Summary: FIST MinIO Client SDK for Python
Author: ccyy
Author-email: 1805878415@qq.com
License: Apache-2.0
Classifier: Programming Language :: Python
Classifier: Programming Language :: Python :: 3.7
Classifier: Programming Language :: Python :: 3.8
Classifier: Programming Language :: Python :: 3.9
Classifier: Programming Language :: Python :: 3.10
Classifier: Programming Language :: Python :: 3.11
Classifier: License :: OSI Approved :: Apache Software License
Classifier: Operating System :: OS Independent
Requires-Python: >=3.7
License-File: LICENSE
Requires-Dist: minio ==7.2.3
Requires-Dist: pyyaml
Requires-Dist: cryptography
Requires-Dist: tqdm
